whereby_api/__init__.py
whereby_api-0.1.3.dist-info/LICENSE
whereby_api-0.1.3.dist-info/METADATA
whereby_api-0.1.3.dist-info/WHEEL
whereby_api-0.1.3.dist-info/top_level.txt
whereby_api-0.1.3.dist-info/RECORD
