Metadata-Version: 2.1
Name: whereby-api
Version: 0.1.3
Summary: Client for the Whereby API
Home-page: https://github.com/philippbosch/python-whereby-api
Author: Philipp Bosch
Author-email: hello@pb.io
Classifier: Programming Language :: Python :: 3
Classifier: License :: OSI Approved :: MIT License
Classifier: Operating System :: OS Independent
Requires-Python: >=3.7
License-File: LICENSE
Requires-Dist: requests
Requires-Dist: python-dateutil
